fl_manager/components/datasets/torch/__init__.py
fl_manager/components/datasets/torch/py.typed
fl_manager/components/datasets/torch/torch_dataframe_transforms_dataset.py
fl_manager/components/datasets/torch/data/__init__.py
fl_manager/components/datasets/torch/data/torch_transform_dataset.py
fl_manager/components/datasets/torch/data/torch_transforms_dataset.py
fl_manager_components_datasets_torch-0.1.0.dist-info/METADATA
fl_manager_components_datasets_torch-0.1.0.dist-info/WHEEL
fl_manager_components_datasets_torch-0.1.0.dist-info/licenses/LICENSE
fl_manager_components_datasets_torch-0.1.0.dist-info/RECORD
